selgym/__init__.py
selgym/gym.py
selgym/update_gecko.py
selgym-0.1.6.dist-info/LICENSE
selgym-0.1.6.dist-info/METADATA
selgym-0.1.6.dist-info/WHEEL
selgym-0.1.6.dist-info/top_level.txt
selgym-0.1.6.dist-info/RECORD
