Metadata-Version: 2.1
Name: selgym
Version: 0.1.6
Summary: Selenium scripting utility library for building scrapers with geckodriver and Firefox
Home-page: https://github.com/st1vms/selgym
Author: st1vms
Author-email: stefano.maria.salvatore@gmail.com
Classifier: Programming Language :: Python :: 3.9
Classifier: License :: OSI Approved :: MIT License
Classifier: Operating System :: OS Independent
Requires-Python: >=3.9
License-File: LICENSE
Requires-Dist: requests
Requires-Dist: selenium
Requires-Dist: screeninfo
